address_to_line/__init__.py
address_to_line/__main__.py
address_to_line/format.py
address_to_line/functions.py
address_to_line/maps.py
address_to_line/sections.py
address_to_line-0.1.2.dist-info/LICENSE.md
address_to_line-0.1.2.dist-info/METADATA
address_to_line-0.1.2.dist-info/WHEEL
address_to_line-0.1.2.dist-info/top_level.txt
address_to_line-0.1.2.dist-info/RECORD
