Metadata-Version: 2.1
Name: address-to-line
Version: 0.1.2
Summary: Convert addresses to source file and line number
Author: Adam Tuft
License: BSD 3-Clause License
License-File: LICENSE.md
